mcp_search_linkup/__init__.py
mcp_search_linkup/server.py
mcp_search_linkup-0.1.5.dist-info/METADATA
mcp_search_linkup-0.1.5.dist-info/WHEEL
mcp_search_linkup-0.1.5.dist-info/entry_points.txt
mcp_search_linkup-0.1.5.dist-info/licenses/LICENSE
mcp_search_linkup-0.1.5.dist-info/RECORD
