Metadata-Version: 2.4
Name: mcp-search-linkup
Version: 0.1.5
Summary: A MCP server to search web with Linkup
License-File: LICENSE
Requires-Python: >=3.11
Requires-Dist: linkup-sdk>=0.2.0
Requires-Dist: mcp>=1.0.0
